MANIFEST.in
README
__init__.py
__pkginfo__.py
hooks.py
schema.py
schemaperms.py
setup.py
site_cubicweb.py
sobjects.py
testutils.py
uiprops.py
cubicweb_tracker.egg-info/PKG-INFO
cubicweb_tracker.egg-info/SOURCES.txt
cubicweb_tracker.egg-info/dependency_links.txt
cubicweb_tracker.egg-info/not-zip-safe
cubicweb_tracker.egg-info/requires.txt
cubicweb_tracker.egg-info/top_level.txt
data/cubes.tracker.css
data/cubes.tracker.stats.css
data/entypo.eot
data/entypo.svg
data/entypo.ttf
data/entypo.woff
data/icon_bug.gif
data/icon_project.gif
data/icon_story.gif
doc/index.rst
entities/__init__.py
entities/project.py
entities/ticket.py
entities/version.py
i18n/en.po
i18n/es.po
i18n/fr.po
migration/1.10.0_Any.py
migration/1.10.2_Any.py
migration/1.15.0_Any.py
migration/1.15.1_Any.py
migration/1.16.2_Any.py
migration/1.18.0_Any.py
migration/postcreate.py
migration/precreate.py
schema/_regproc.postgres.sql
test/test_tracker.py
views/__init__.py
views/doap.py
views/document.py
views/facets.py
views/forms.py
views/project.py
views/ticket.py
views/version.py