Metadata-Version: 1.0
Name: cubicweb-tracker
Version: 1.18.0
Summary: basic tracker with project, version, ticket for the CubicWeb framework
Home-page: http://www.cubicweb.org/project/cubicweb-tracker
Author: LOGILAB S.A. (Paris, FRANCE)
Author-email: contact@logilab.fr
License: LGPL
Platform: UNKNOWN
